{
    "AX": {
        "error": 0.009264394116252024, 
        "fit": "average", 
        "value": -0.06295623036227577
    }, 
    "CDD": {
        "error": 1.406061743976957e-05, 
        "fit": "average", 
        "value": 0.00015661534562241285
    }, 
    "H1": {
        "error": 0.009945605705434105, 
        "fit": "average", 
        "value": 0.04480048821181602
    }, 
    "H2": {
        "error": 0.011546803181662011, 
        "fit": "average", 
        "value": 0.20656225441101317
    }, 
    "L1": {
        "error": 0.011884842334019747, 
        "fit": "average", 
        "value": -0.17751058655412635
    }, 
    "L2": {
        "error": 0.012081785892087334, 
        "fit": "average", 
        "value": 0.09117521472762746
    }
}