{
    "Ar36": {
        "error": 0.00060089028890300078, 
        "fit": "parabolic", 
        "value": 0.059627540128981263
    }, 
    "Ar37": {
        "error": 0.013965033449319285, 
        "fit": "linear", 
        "value": 0.13919901970421666
    }, 
    "Ar38": {
        "error": 0.019560375002488618, 
        "fit": "linear", 
        "value": 0.77387237693165023
    }, 
    "Ar39": {
        "error": 0.016494648287018032, 
        "fit": "parabolic", 
        "value": 70.140755635272143
    }, 
    "Ar40": {
        "error": 0.16202964839396208, 
        "fit": "parabolic", 
        "value": 4550.6359315888394
    }, 
    "Ar41": {
        "error": 0.0064592507007754972, 
        "fit": "average", 
        "value": 0.033148500665702157
    }
}