{
    "Ar36": {
        "error": 0.00050942105352173481, 
        "fit": "parabolic", 
        "value": 0.04858870868087635
    }, 
    "Ar37": {
        "error": 0.014384774398338272, 
        "fit": "linear", 
        "value": 0.13309663881900863
    }, 
    "Ar38": {
        "error": 0.022293058692136183, 
        "fit": "linear", 
        "value": 0.4320489788046018
    }, 
    "Ar39": {
        "error": 0.013687695651808919, 
        "fit": "parabolic", 
        "value": 42.082066725870689
    }, 
    "Ar40": {
        "error": 0.11222611178223542, 
        "fit": "parabolic", 
        "value": 2728.7168391892119
    }, 
    "Ar41": {
        "error": 0.0065329628830678782, 
        "fit": "average", 
        "value": 0.010868706201581518
    }
}