{
    "AX": {
        "error": 0.058585283952434654, 
        "fit": "average_SEM", 
        "value": -0.01732759435750874
    }, 
    "CDD": {
        "error": 0.0001490170594587706, 
        "fit": "average_SEM", 
        "value": 0.0001344090703544983
    }, 
    "H1": {
        "error": 0.11930460749390426, 
        "fit": "average_SEM", 
        "value": 0.04810565095079558
    }, 
    "H2": {
        "error": 0.13467040481090112, 
        "fit": "average_SEM", 
        "value": -0.30115860753382245
    }, 
    "L1": {
        "error": 0.17071523221548937, 
        "fit": "average_SEM", 
        "value": -0.06372573719903206
    }, 
    "L2": {
        "error": 0.1354670139283455, 
        "fit": "average_SEM", 
        "value": 0.008080894827920323
    }
}